logipass/__init__.py
logipass/app.py
logipass/main.py
logipass-0.0.1.dist-info/METADATA
logipass-0.0.1.dist-info/WHEEL
logipass-0.0.1.dist-info/entry_points.txt
logipass-0.0.1.dist-info/top_level.txt
logipass-0.0.1.dist-info/RECORD
